mobidic_mpa/__init__.py
mobidic_mpa-1.3.0.data/scripts/mpa
mobidic_mpa-1.3.0.dist-info/LICENSE
mobidic_mpa-1.3.0.dist-info/METADATA
mobidic_mpa-1.3.0.dist-info/WHEEL
mobidic_mpa-1.3.0.dist-info/top_level.txt
mobidic_mpa-1.3.0.dist-info/RECORD
