Metadata-Version: 2.1
Name: mobidic-mpa
Version: 1.3.0
Summary: MPA: MoBiDiC Prioritization Algorithm
Home-page: https://mobidic.github.io/MPA/
Author: Mobidic
Author-email: c-vangoethem@chu-montpellier.fr
Project-URL: Bug Reports, https://github.com/mobidic/MPA/issues
Project-URL: Source, https://github.com/mobidic/MPA
Classifier: Programming Language :: Python :: 3
Classifier: Programming Language :: Python :: 3.6
Classifier: License :: OSI Approved :: MIT License
Classifier: Operating System :: OS Independent
Classifier: Development Status :: 5 - Production/Stable
Classifier: Programming Language :: Python :: Implementation :: PyPy
Classifier: Topic :: Scientific/Engineering :: Bio-Informatics
License-File: LICENSE
Requires-Dist: vcfpy (>=0.13.4)
Requires-Dist: tqdm (>=4.59.0)
Requires-Dist: pysam (>=0.19.1)
